[
    {
        "Rank": "1",
        "Name": "Itahari (Sub-Metro)",
        "Nepali": "ईटहरी",
        "District": "Sunsari District",
        "Geocode": "11306",
        "Population (2011)": "140,517",
        "Area": "93.78",
        "Website": "[17]"
    },
    {
        "Rank": "2",
        "Name": "Dharan (Sub-Metro)",
        "Nepali": "धरान",
        "District": "Sunsari District",
        "Geocode": "11301",
        "Population (2011)": "137,705",
        "Area": "192.32",
        "Website": "[18]"
    }
]